{
    "DNDConfig": null,
    "_height_": {
        "type": "ref",
        "value": "preferred"
    },
    "_left_": {
        "type": "string",
        "value": "0dp"
    },
    "_margin_": [
        0,
        0,
        0,
        0
    ],
    "_orientation_": 6,
    "_padding_": [
        0,
        0,
        0,
        0
    ],
    "_percent_": true,
    "_skin_": "s24cd75b0add4836bd6270f0a56e9516",
    "_top_": {
        "type": "string",
        "value": "10dp"
    },
    "_width_": {
        "type": "string",
        "value": "88%"
    },
    "allboxes": [],
    "autogrowmode": 1,
    "canUpdateUI": true,
    "centerx": {
        "type": "string",
        "value": "50%"
    },
    "children": [
        "flxVacCer",
        "flxTestCer",
        "flxRec1",
        "flxRec2"
    ],
    "clipbounds": false,
    "containerweight": 100,
    "enablescrolling": true,
    "id": "flxCer",
    "info": null,
    "iscustomlayout": false,
    "isvisible": true,
    "kuid": "d6862a6eff9a48b49f68e8c192471072",
    "layouttype": 4,
    "name": "kony.ui.FlexContainer",
    "parent": "flxJohn",
    "pf": "frmCertificate",
    "retaincontentalignment": false,
    "retainflexpositionproperties": false,
    "retainflowhorizontalalignment": false,
    "snapgridsize": 10,
    "snaptogrid": true,
    "wType": "FlexContainer",
    "widgetalignment": 1,
    "zindex": 1
}